NeoMetaTracker/__init__.py
NeoMetaTracker/capture_point.py
NeoMetaTracker/graph_scheme.py
NeoMetaTracker/neo_meta_logger.py
NeoMetaTracker/visualizer/__init__.py
NeoMetaTracker/visualizer/_base_visualizer.py
NeoMetaTracker/visualizer/graphiz_visualizer.py
NeoMetaTracker/visualizer/networkx_visualizer.py
NeoMetaTracker-0.0.11.dist-info/LICENSE.md
NeoMetaTracker-0.0.11.dist-info/METADATA
NeoMetaTracker-0.0.11.dist-info/WHEEL
NeoMetaTracker-0.0.11.dist-info/top_level.txt
NeoMetaTracker-0.0.11.dist-info/RECORD
