Metadata-Version: 2.1
Name: NeoMetaTracker
Version: 0.0.11
Summary: Track and visualize changes in a Neo4j database schema
Home-page: https://git.connect.dzd-ev.de/dzdpythonmodules/neo4j-meta-logger
Author: Tim Bleimehl
Author-email: tim.bleimehl@helmholtz-muenchen.de
License: MIT
Platform: UNKNOWN
Requires-Python: >=3.9
License-File: LICENSE.md
Requires-Dist: py2neo
Requires-Dist: DZDUtils
